Metadata-Version: 2.1
Name: drg2txt
Version: 0.3.0
Summary: Map MS-DRG v38.1 DRG/MDC numeric codes to their text description
Home-page: https://github.com/banderlog/drg2txt
Maintainer: Kabakov Borys
License: MIT
Platform: UNKNOWN
Classifier: Development Status :: 5 - Production/Stable
Classifier: Environment :: Console
Classifier: Intended Audience :: Science/Research
Classifier: Programming Language :: Python :: 3
Classifier: Operating System :: POSIX :: Linux
Classifier: Topic :: Scientific/Engineering
